{
  "collapse-filter": false,
  "search": "",
  "showTags": false,
  "showAttachments": false,
  "hideUnresolved": false,
  "showOrphans": true,
  "collapse-color-groups": false,
  "colorGroups": [
    {
      "query": "path:Device",
      "color": {
        "a": 1,
        "rgb": 14701138
      }
    },
    {
      "query": "path:서비스",
      "color": {
        "a": 1,
        "rgb": 5401056
      }
    }
  ],
  "collapse-display": true,
  "showArrow": false,
  "textFadeMultiplier": 0,
  "nodeSizeMultiplier": 1,
  "lineSizeMultiplier": 1,
  "collapse-forces": false,
  "centerStrength": 0.6140625,
  "repelStrength": 20,
  "linkStrength": 1,
  "linkDistance": 142,
  "scale": 0.6554983534946925,
  "close": true
}